README.md
setup.py
rto/__init__.py
rto/main.py
rto.egg-info/PKG-INFO
rto.egg-info/SOURCES.txt
rto.egg-info/dependency_links.txt
rto.egg-info/entry_points.txt
rto.egg-info/not-zip-safe
rto.egg-info/requires.txt
rto.egg-info/top_level.txt