Metadata-Version: 1.1
Name: rto
Version: 1.0
Summary: Open Redmine ticket of myself to browser.
Home-page: https://github.com/sassy/rto
Author: Satoshi Watanabe
Author-email: sassy.watanabe@gmail.com
License: MIT
Platform: UNKNOWN
Classifier: Environment :: Console
Classifier: Intended Audience :: Developers
Classifier: Operating System :: MacOS :: MacOS X
Classifier: Operating System :: Microsoft :: Windows
Classifier: Programming Language :: Python
